{
  "Header": {
    "Original": "[02 May 2023] DLA-3413-1 libdatetime-timezone-perl - new timezone database",
    "Line": 987,
    "ID": "DLA-3413-1",
    "Description": "libdatetime-timezone-perl - new timezone database"
  },
  "Annotations": [
    {
      "Original": "[buster] - libdatetime-timezone-perl 1:2.23-1+2023c",
      "Line": 988,
      "Type": "package",
      "Release": "buster",
      "Package": "libdatetime-timezone-perl",
      "Kind": "fixed",
      "Version": "1:2.23-1+2023c"
    }
  ]
}